avereno/__init__.py
avereno/core.py
avereno/version.py
avereno-0.1.2.dist-info/LICENSE
avereno-0.1.2.dist-info/METADATA
avereno-0.1.2.dist-info/WHEEL
avereno-0.1.2.dist-info/top_level.txt
avereno-0.1.2.dist-info/RECORD
