Metadata-Version: 2.1
Name: avereno
Version: 0.1.2
Summary: Yet another retry utility in Python
Home-page: https://github.com/hei-school/avereno
Author: HEI
Author-email: contact@hei.school
License: MIT
Platform: UNKNOWN
